knex/__init__.py
knex/__main__.py
knex/parsers.py
knex/utils.py
knex-0.5.0.dist-info/LICENSE
knex-0.5.0.dist-info/WHEEL
knex-0.5.0.dist-info/METADATA
knex-0.5.0.dist-info/RECORD
